modelcomp/__init__.py
modelcomp/analysis.py
modelcomp/plotter.py
modelcomp/read.py
modelcomp/utilities.py
modelcomp/write.py
modelcomp/models/__init__.py
modelcomp/models/knn.py
modelcomp/models/logistic_regression.py
modelcomp/models/random_forest.py
modelcomp/models/svm.py
modelcomp/models/xgboost.py
modelcomp-0.0.1a1.dist-info/LICENSE
modelcomp-0.0.1a1.dist-info/METADATA
modelcomp-0.0.1a1.dist-info/WHEEL
modelcomp-0.0.1a1.dist-info/top_level.txt
modelcomp-0.0.1a1.dist-info/RECORD
