Metadata-Version: 2.1
Name: modelcomp
Version: 0.0.1a1
Summary: Compare between performances of machine learning models with ease.
Author-email: Gil Ramot <gilramot3@gmail.com>
Maintainer-email: Gil Ramot <gilramot3@gmail.com>
License: MIT License
Project-URL: Repository, https://github.com/gilramot/modelcomp
Project-URL: Issues, https://github.com/gilramot/modelcomp/issues
Project-URL: Appendix, https://github.com/gilramot/modelcomp-appendix
Classifier: Programming Language :: Python :: 3 :: Only
Classifier: Programming Language :: Python :: 3
Classifier: Programming Language :: Python :: 3.6
Classifier: Programming Language :: Python :: 3.7
Classifier: Programming Language :: Python :: 3.8
Classifier: Programming Language :: Python :: 3.9
Classifier: Programming Language :: Python :: 3.10
Classifier: Programming Language :: Python :: 3.11
Classifier: Programming Language :: Python :: 3.12
Classifier: License :: OSI Approved :: MIT License
Classifier: Operating System :: OS Independent
Requires-Python: >=3.6
License-File: LICENSE
Requires-Dist: matplotlib
Requires-Dist: numpy
Requires-Dist: pandas
Requires-Dist: scikit-learn
Requires-Dist: shap
Requires-Dist: xgboost
Requires-Dist: seaborn
